larch/.DS_Store
larch/__init__.py
larch/_version.py
larch/apps.py
larch/builtins.py
larch/closure.py
larch/inputText.py
larch/interpreter.py
larch/larchlib.py
larch/shell.py
larch/site_config.py
larch/symboltable.py
larch/version.py
larch/xmlrpc_server.py
larch/bin/__init__.py
larch/bin/darwin64/README
larch/bin/darwin64/feff6l
larch/bin/darwin64/feff8l.py
larch/bin/darwin64/feff8l.sh
larch/bin/darwin64/feff8l_ff2x
larch/bin/darwin64/feff8l_genfmt
larch/bin/darwin64/feff8l_pathfinder
larch/bin/darwin64/feff8l_pot
larch/bin/darwin64/feff8l_rdinp
larch/bin/darwin64/feff8l_xsph
larch/bin/darwin64/json_module.mod
larch/bin/darwin64/libcldata.dylib
larch/bin/darwin64/libfeff6.dylib
larch/bin/darwin64/libfeff8lpath.dylib
larch/bin/darwin64/libfeff8lpotph.dylib
larch/bin/darwin64/libgcc_s.1.dylib
larch/bin/darwin64/libgfortran.5.dylib
larch/bin/darwin64/libjsonfortran.a
larch/bin/darwin64/libonepath.dylib
larch/bin/darwin64/libpotph.dylib
larch/bin/darwin64/libquadmath.0.dylib
larch/bin/darwin64/libxdifile.dylib
larch/bin/darwin64/pathfix.py
larch/bin/linux64/feff6l
larch/bin/linux64/feff8l.py
larch/bin/linux64/feff8l.sh
larch/bin/linux64/feff8l_ff2x
larch/bin/linux64/feff8l_genfmt
larch/bin/linux64/feff8l_pathfinder
larch/bin/linux64/feff8l_pot
larch/bin/linux64/feff8l_rdinp
larch/bin/linux64/feff8l_xsph
larch/bin/linux64/json_module.mod
larch/bin/linux64/libcldata.so
larch/bin/linux64/libfeff6.so
larch/bin/linux64/libfeff8lpath.so
larch/bin/linux64/libfeff8lpotph.so
larch/bin/linux64/libgcc_s_f8.so
larch/bin/linux64/libgfortran_f8.so
larch/bin/linux64/libjsonfortran.a
larch/bin/linux64/libonepath.so
larch/bin/linux64/libpotph.so
larch/bin/linux64/libquadmath_f8.so
larch/bin/linux64/libxdifile.so
larch/bin/linux64/pathfix.sh
larch/bin/win64/cldata.dll
larch/bin/win64/feff6.dll
larch/bin/win64/feff6l.exe
larch/bin/win64/feff8l.bat
larch/bin/win64/feff8l.py
larch/bin/win64/feff8l_ff2x.exe
larch/bin/win64/feff8l_genfmt.exe
larch/bin/win64/feff8l_pathfinder.exe
larch/xraylarch.egg-info/PKG-INFO
larch/xraylarch.egg-info/SOURCES.txt
larch/xraylarch.egg-info/dependency_links.txt
larch/xraylarch.egg-info/entry_points.txt
larch/xraylarch.egg-info/not-zip-safe
larch/xraylarch.egg-info/requires.txt
larch/xraylarch.egg-info/top_level.txt
xraylarch-2025.3.0.dist-info/licenses/LICENSE
xraylarch-2025.3.0.dist-info/METADATA
xraylarch-2025.3.0.dist-info/WHEEL
xraylarch-2025.3.0.dist-info/entry_points.txt
xraylarch-2025.3.0.dist-info/top_level.txt
xraylarch-2025.3.0.dist-info/RECORD
