Metadata-Version: 2.4
Name: xraylarch
Version: 2025.3.0
Summary: Synchrotron X-ray data analysis in python
Author-email: Matthew Newville <newville@cars.uchicago.edu>, Mauro Rovezzi <mauro.rovezzi@esrf.fr>, Bruce Ravel <bravel@nist.gov>, Margaret Koker <margaret.koker@lawrence.edu>
License-Expression: MIT
Project-URL: Homepage,  https://github.com/xraypy/xraylarch
Project-URL: Documentation, https://xraypy.github.io/xraylarch/
Project-URL: Tracker, https://github.com/xraypy/xraylarch/issues
Keywords: X-ray,XAS,XRF,XRD,Physics,Fitting
Classifier: Development Status :: 5 - Production/Stable
Classifier: Intended Audience :: Developers
Classifier: Operating System :: OS Independent
Classifier: Programming Language :: Python :: 3.10
Classifier: Programming Language :: Python :: 3.11
Classifier: Programming Language :: Python :: 3.12
Classifier: Programming Language :: Python :: 3.13
Requires-Python: >=3.10
License-File: LICENSE
Requires-Dist: numpy>=1.23
Requires-Dist: scipy>=1.12
Requires-Dist: lmfit>=1.3.1
Requires-Dist: asteval>=1.0.6
Requires-Dist: uncertainties>=3.2.1
Requires-Dist: pyshortcuts>=1.9.5
Requires-Dist: xraydb>=4.5.6
Requires-Dist: larixite>=2025.5.1
Requires-Dist: silx>=0.15.2
Requires-Dist: matplotlib>=3.8
Requires-Dist: sqlalchemy>=2.0
Requires-Dist: sqlalchemy_utils
Requires-Dist: h5py>=3.5
Requires-Dist: hdf5plugin
Requires-Dist: pillow>=8.3.2
Requires-Dist: numdifftools>=0.9.41
Requires-Dist: packaging
Requires-Dist: pip
Requires-Dist: pyyaml
Requires-Dist: tomli
Requires-Dist: tomli_w
Requires-Dist: termcolor
Requires-Dist: dill
Requires-Dist: imageio
Requires-Dist: charset-normalizer
Requires-Dist: requests
Requires-Dist: scikit-image
Requires-Dist: scikit-learn
Requires-Dist: psutil
Requires-Dist: fabio
Requires-Dist: pyfai
Requires-Dist: tabulate
Provides-Extra: dev
Requires-Dist: build; extra == "dev"
Requires-Dist: twine; extra == "dev"
Requires-Dist: pre-commit; extra == "dev"
Requires-Dist: pytest; extra == "dev"
Requires-Dist: pytest-xvfb; extra == "dev"
Requires-Dist: pytest-cov; extra == "dev"
Requires-Dist: coverage; extra == "dev"
Provides-Extra: doc
Requires-Dist: Sphinx; extra == "doc"
Requires-Dist: sphinx-copybutton; extra == "doc"
Requires-Dist: sphinxcontrib-video; extra == "doc"
Requires-Dist: sphinxcontrib-bibtex; extra == "doc"
Requires-Dist: sphinxcontrib-argdoc; extra == "doc"
Provides-Extra: wxgui
Requires-Dist: wxpython>=4.2.2; extra == "wxgui"
Requires-Dist: wxmplot>=2025.1.5; extra == "wxgui"
Requires-Dist: wxutils>=0.3.6; extra == "wxgui"
Requires-Dist: darkdetect; extra == "wxgui"
Provides-Extra: qtgui
Requires-Dist: PyQt5; extra == "qtgui"
Requires-Dist: pyqtwebengine; extra == "qtgui"
Requires-Dist: pyqtgraph; extra == "qtgui"
Provides-Extra: epics
Requires-Dist: pyepics>=3.5.7; extra == "epics"
Requires-Dist: psycopg2-binary; extra == "epics"
Provides-Extra: jupyter
Requires-Dist: jupyter_core>=5.0; extra == "jupyter"
Requires-Dist: jupyter_client; extra == "jupyter"
Requires-Dist: jupyter_server; extra == "jupyter"
Requires-Dist: notebook; extra == "jupyter"
Requires-Dist: nbformat; extra == "jupyter"
Requires-Dist: ipywidgets; extra == "jupyter"
Requires-Dist: plotly; extra == "jupyter"
Requires-Dist: bokeh; extra == "jupyter"
Requires-Dist: py3dmol; extra == "jupyter"
Provides-Extra: larix
Requires-Dist: xraylarch[jupyter,wxgui]; extra == "larix"
Provides-Extra: all
Requires-Dist: xraylarch[dev,doc,epics,jupyter,qtgui,wxgui]; extra == "all"
Dynamic: license-file
